py_awesome_scripts/__init__.py
py_awesome_scripts/filedate.py
py_awesome_scripts/filelevel.py
py_awesome_scripts/folderback.py
py_awesome_scripts/folderzip.py
py_awesome_scripts/img2pdf.py
py_awesome_scripts/imgr.py
py_awesome_scripts/latexfmt.py
py_awesome_scripts/pdfenc.py
py_awesome_scripts/pdfmerge.py
py_awesome_scripts/pdfsplit.py
py_awesome_scripts/scraplinks.py
py_awesome_scripts/brucetonw/brucetonw.py
py_awesome_scripts/brucetonw/depends/BrucetonDialog.py
py_awesome_scripts/brucetonw/depends/BrucetonDialog.ui
py_awesome_scripts/brucetonw/depends/__init__.py
py_awesome_scripts/brucetonw/depends/ui_BrucetonDialog.py
py_awesome_scripts/checksumw/__init__.py
py_awesome_scripts/checksumw/checksumw.py
py_awesome_scripts/checksumw/deps/__init__.py
py_awesome_scripts/checksumw/deps/checksum.ui
py_awesome_scripts/checksumw/deps/ui_checksum.py
py_awesome_scripts/cnmapw/CNMap.py
py_awesome_scripts/cnmapw/deps/CNMapViewer.py
py_awesome_scripts/cnmapw/deps/CNMapViewer.ui
py_awesome_scripts/cnmapw/deps/__init__.py
py_awesome_scripts/cnmapw/deps/ui_CNMapViewer.py
py_awesome_scripts/filesearcherw/__init__.py
py_awesome_scripts/filesearcherw/filesearcherw.py
py_awesome_scripts/filesearcherw/assets/templates/后缀分析.json
py_awesome_scripts/filesearcherw/deps/__init__.py
py_awesome_scripts/filesearcherw/deps/config.py
py_awesome_scripts/filesearcherw/deps/indexer.py
py_awesome_scripts/filesearcherw/deps/gui/ButtonDelegate.py
py_awesome_scripts/filesearcherw/deps/gui/FileTreeModel.py
py_awesome_scripts/filesearcherw/deps/gui/ParserOptionDialog.py
py_awesome_scripts/filesearcherw/deps/gui/ParserOptionDialog.ui
py_awesome_scripts/filesearcherw/deps/gui/SearchWindow.py
py_awesome_scripts/filesearcherw/deps/gui/SearchWindow.ui
py_awesome_scripts/filesearcherw/deps/gui/__init__.py
py_awesome_scripts/filesearcherw/deps/gui/ui_ParserOptionDialog.py
py_awesome_scripts/filesearcherw/deps/gui/ui_SearchWindow.py
py_awesome_scripts/filesearcherw/deps/readers/__init__.py
py_awesome_scripts-0.3.dist-info/METADATA
py_awesome_scripts-0.3.dist-info/WHEEL
py_awesome_scripts-0.3.dist-info/RECORD
