Metadata-Version: 2.3
Name: py-awesome-scripts
Version: 0.3
Summary: Awesome python script tools.
Requires-Python: <3.9,>=3.8
Requires-Dist: chardet>=5.2.0
Requires-Dist: docx2pdf>=0.1.8
Requires-Dist: jieba>=0.42.1
Requires-Dist: numpy>=1.24.4
Requires-Dist: openpyxl>=3.1.5
Requires-Dist: pdfplumber>=0.11.4
Requires-Dist: pycdlib>=1.14.0
Requires-Dist: pyfiglet>=0.8.post1
Requires-Dist: pygame>=2.6.1
Requires-Dist: pypdf>=5.0.1
Requires-Dist: pyside2>=5.15.2.1
Requires-Dist: python-docx>=1.1.2
Requires-Dist: requests>=2.32.3
Requires-Dist: rtoml>=0.11.0
Requires-Dist: torch>=2.4.1
Requires-Dist: torchaudio>=2.4.1
Requires-Dist: torchvision>=0.19.1
Requires-Dist: whoosh>=2.7.4
Requires-Dist: xlrd>=2.0.1
